main.py
mcp_miaocontrol_wsd-0.1.2.dist-info/METADATA
mcp_miaocontrol_wsd-0.1.2.dist-info/WHEEL
mcp_miaocontrol_wsd-0.1.2.dist-info/entry_points.txt
mcp_miaocontrol_wsd-0.1.2.dist-info/top_level.txt
mcp_miaocontrol_wsd-0.1.2.dist-info/RECORD
